Metadata-Version: 1.0
Name: proba-publ-proj
Version: 0.0.0
Summary: fajny program
Home-page: UNKNOWN
Author: Monika
Author-email: monikaa_sz@interia.pl
License: UNKNOWN
Platform: UNKNOWN
